asc.py
ascendant-1.0.1.dist-info/licenses/LICENSE
ascendant-1.0.1.dist-info/METADATA
ascendant-1.0.1.dist-info/WHEEL
ascendant-1.0.1.dist-info/entry_points.txt
ascendant-1.0.1.dist-info/top_level.txt
ascendant-1.0.1.dist-info/RECORD
