Metadata-Version: 2.4
Name: ascendant
Version: 1.0.1
Summary: a small astrology CLI that prints the current local ascendant within the tropical zodiac
Author-email: sailorfe <sailorf@proton.me>
License-Expression: AGPL-3.0-or-later
Project-URL: Repository, https://codeberg.org/sailorfe/asc
Keywords: astrology,horoscope
Classifier: Development Status :: 3 - Alpha
Classifier: Intended Audience :: Religion
Classifier: Programming Language :: Python :: 3
Classifier: Programming Language :: Python :: 3.13
Classifier: Topic :: Religion
Requires-Python: >=3.0
License-File: LICENSE
Requires-Dist: pyswisseph
Dynamic: license-file
